{
  "schema_version": "1.0",
  "ok": true,
  "skill_dir": ".previews/yao-meta-skill-v2-report-demo/geo-content-brief-skill",
  "generated_at": "2026-06-15",
  "summary": {
    "waiver_count": 0,
    "active_count": 0,
    "expired_count": 0,
    "invalid_count": 0,
    "covered_gate_count": 0,
    "covered_gate_keys": [],
    "waiver_candidate_count": 0,
    "waiverable_open_count": 0,
    "non_waivable_count": 0
  },
  "policy": {
    "blocker_waivers_allowed": false,
    "minimum_reason_chars": 20,
    "expires_required": true,
    "known_gate_keys": [
      "context-budget",
      "intent-canvas",
      "operations-loop",
      "output-lab",
      "permission-gates",
      "permission-runtime",
      "registry-audit",
      "release-notes",
      "runtime-matrix",
      "skill-atlas",
      "trigger-lab",
      "trust-report"
    ]
  },
  "waivers": [],
  "waiver_candidates": [],
  "failures": [],
  "warnings": [],
  "artifacts": {
    "json": ".previews/yao-meta-skill-v2-report-demo/geo-content-brief-skill/reports/review_waivers.json",
    "markdown": ".previews/yao-meta-skill-v2-report-demo/geo-content-brief-skill/reports/review_waivers.md"
  }
}
